pymctp_exerciser_qemu/__init__.py
pymctp_exerciser_qemu/qemu_i2c_netdev.py
pymctp_exerciser_qemu/qemu_i3c_chardev.py
pymctp_exerciser_qemu-0.2.5.dist-info/METADATA
pymctp_exerciser_qemu-0.2.5.dist-info/WHEEL
pymctp_exerciser_qemu-0.2.5.dist-info/entry_points.txt
pymctp_exerciser_qemu-0.2.5.dist-info/RECORD
