Metadata-Version: 2.4
Name: pymctp-exerciser-qemu
Version: 0.2.5
Summary: QEMU I2C/I3C exerciser for pymctp
Project-URL: Documentation, https://github.com/jls5177/pymctp#readme
Project-URL: Issues, https://github.com/jls5177/pymctp/issues
Project-URL: Source, https://github.com/jls5177/pymctp
Author-email: Justin Simon <justin@simonctl.com>
License: MIT
Keywords: i2c,i3c,mctp,qemu,virtualization
Classifier: Development Status :: 4 - Beta
Classifier: Intended Audience :: Developers
Classifier: Programming Language :: Python
Classifier: Programming Language :: Python :: 3.8
Classifier: Programming Language :: Python :: 3.9
Classifier: Programming Language :: Python :: 3.10
Classifier: Programming Language :: Python :: 3.11
Classifier: Programming Language :: Python :: 3.12
Classifier: Programming Language :: Python :: Implementation :: CPython
Classifier: Topic :: Software Development :: Libraries
Classifier: Topic :: System :: Emulators
Requires-Python: >=3.8
Requires-Dist: crc8>=0.1.0
Requires-Dist: pymctp>=0.2.5
